message_provider/__init__.py
message_provider/discord_message_provider.py
message_provider/fastapi_message_provider.py
message_provider/jira_message_provider.py
message_provider/message_provider.py
message_provider/slack_message_provider.py
message_provider/webhook.py
message_provider/examples/__init__.py
message_provider/examples/discord_example.py
message_provider/examples/jira_example.py
message_provider/examples/polling_client_example.py
message_provider/examples/relay_client_example.py
message_provider/examples/relay_example.py
message_provider/examples/slack_example.py
message_provider/relay/__init__.py
message_provider/relay/relay_client.py
message_provider/relay/relay_hub.py
message_provider/relay/relay_message_provider.py
message_provider/tests/__init__.py
message_provider/tests/conftest.py
message_provider/tests/test_discord_provider.py
message_provider/tests/test_fastapi_provider.py
message_provider/tests/test_jira_provider.py
message_provider/tests/test_message_provider.py
message_provider/tests/test_relay.py
message_provider/tests/test_slack_provider.py
omni_message_provider-0.2.0.dist-info/licenses/LICENSE
omni_message_provider-0.2.0.dist-info/METADATA
omni_message_provider-0.2.0.dist-info/WHEEL
omni_message_provider-0.2.0.dist-info/top_level.txt
omni_message_provider-0.2.0.dist-info/RECORD
