Metadata-Version: 2.4
Name: omni-message-provider
Version: 0.2.0
Summary: Unified message provider interface for Discord, Slack, Jira, and custom platforms with distributed relay support
Author-email: Adam Sanchez <agentpython@proton.me>
Maintainer-email: Adam Sanchez <agentpython@proton.me>
License-Expression: MIT
Project-URL: Homepage, https://github.com/AgentSanchez/omni-message-provider
Project-URL: Documentation, https://github.com/AgentSanchez/omni-message-provider#readme
Project-URL: Repository, https://github.com/AgentSanchez/omni-message-provider
Project-URL: Issues, https://github.com/AgentSanchez/omni-message-provider/issues
Keywords: messaging,discord,slack,jira,chatbot,websocket,relay
Classifier: Development Status :: 3 - Alpha
Classifier: Intended Audience :: Developers
Classifier: Programming Language :: Python :: 3
Classifier: Programming Language :: Python :: 3.9
Classifier: Programming Language :: Python :: 3.10
Classifier: Programming Language :: Python :: 3.11
Classifier: Programming Language :: Python :: 3.12
Classifier: Topic :: Communications :: Chat
Classifier: Topic :: Software Development :: Libraries :: Python Modules
Requires-Python: >=3.9
License-File: LICENSE
Requires-Dist: fastapi>=0.104.0
Requires-Dist: uvicorn>=0.24.0
Requires-Dist: pydantic>=2.0.0
Requires-Dist: httpx>=0.25.0
Requires-Dist: requests>=2.31.0
Requires-Dist: websockets>=11.0
Requires-Dist: msgpack>=1.0.0
Provides-Extra: discord
Requires-Dist: discord.py>=2.3.0; extra == "discord"
Provides-Extra: slack
Requires-Dist: slack-bolt>=1.18.0; extra == "slack"
Requires-Dist: slack-sdk>=3.23.0; extra == "slack"
Provides-Extra: jira
Requires-Dist: jira>=3.5.0; extra == "jira"
Provides-Extra: all
Requires-Dist: discord.py>=2.3.0; extra == "all"
Requires-Dist: slack-bolt>=1.18.0; extra == "all"
Requires-Dist: slack-sdk>=3.23.0; extra == "all"
Requires-Dist: jira>=3.5.0; extra == "all"
Provides-Extra: dev
Requires-Dist: pytest>=7.4.0; extra == "dev"
Requires-Dist: pytest-asyncio>=0.21.0; extra == "dev"
Requires-Dist: pytest-cov>=4.1.0; extra == "dev"
Requires-Dist: black>=23.0.0; extra == "dev"
Requires-Dist: ruff>=0.1.0; extra == "dev"
Requires-Dist: mypy>=1.5.0; extra == "dev"
Requires-Dist: discord.py>=2.3.0; extra == "dev"
Requires-Dist: slack-bolt>=1.18.0; extra == "dev"
Requires-Dist: slack-sdk>=3.23.0; extra == "dev"
Requires-Dist: jira>=3.5.0; extra == "dev"
Dynamic: license-file
